Metadata-Version: 2.1
Name: topsis-Siddharth-102003707
Version: 1.0
Summary: topsis implementation
Home-page: UNKNOWN
Author: Siddharth Chaudhary
Author-email: siddharthchaudhary0007@gmail.com
License: UNKNOWN
Platform: UNKNOWN
Classifier: Programming Language :: Python :: 3
Classifier: License :: OSI Approved :: MIT License
Classifier: Operating System :: OS Independent
Requires-Python: >=3.6
License-File: LICENSE.txt
